ok_serial/__init__.py
ok_serial/_connection.py
ok_serial/_exceptions.py
ok_serial/_locking.py
ok_serial/_scanning.py
ok_serial/_timeout_math.py
ok_serial/_tracker.py
ok_serial/okserial_cli.py
ok_serial-0.2.dist-info/WHEEL
ok_serial-0.2.dist-info/entry_points.txt
ok_serial-0.2.dist-info/METADATA
ok_serial-0.2.dist-info/RECORD
