Metadata-Version: 2.3
Name: ok-serial
Version: 0.2
Summary: Serial port library (PySerial wrapper) with more features
Author: Dan Egnor
Author-email: Dan Egnor <egnor@ofb.net>
Requires-Dist: beartype>=0.22.9
Requires-Dist: natsort>=8.4.0
Requires-Dist: ok-logging-setup>=0.11
Requires-Dist: pyserial>=3.5
Requires-Dist: types-pyserial>=3.5.0.20251001
Requires-Python: >=3.10
Project-URL: Homepage, https://github.com/egnor/ok-py-serial#readme
Project-URL: Repository, https://github.com/egnor/ok-py-serial.git
